django_auto_rest_project-0.5.3.dist-info/DESCRIPTION.rst
django_auto_rest_project-0.5.3.dist-info/METADATA
django_auto_rest_project-0.5.3.dist-info/RECORD
django_auto_rest_project-0.5.3.dist-info/WHEEL
django_auto_rest_project-0.5.3.dist-info/entry_points.txt
django_auto_rest_project-0.5.3.dist-info/metadata.json
django_auto_rest_project-0.5.3.dist-info/top_level.txt
robot_rest/__init__.py
robot_rest/requirements.txt
robot_rest/robot_rest.py
robot_rest/urls.tpl
robot_rest/settings/__init__.tpl
robot_rest/settings/defaults.tpl
robot_rest/settings/dev.tpl
robot_rest/settings/production.tpl
robot_rest/settings/tests.tpl
robot_rest/tests/__init__.tpl
robot_rest/tests/settingstest.tpl
robot_rest/tests/test_rest_api.tpl
