Metadata-Version: 2.0
Name: django-auto-rest-project
Version: 0.5.3
Summary: This tool provide a way to build Django RESTful projects based your database
Home-page: https://github.com/AlexandreProenca/django-auto-rest-project
Author: Alexandre Proença
Author-email: alexandre.proenca@hotmail.com.br
License: MIT
Keywords: django
Platform: UNKNOWN
Classifier: Development Status :: 2 - Pre-Alpha
Classifier: Environment :: Web Environment
Classifier: Framework :: Django
Classifier: Intended Audience :: Developers
Classifier: License :: OSI Approved :: MIT License
Classifier: Operating System :: OS Independent
Classifier: Programming Language :: Python
Classifier: Programming Language :: Python :: 3
Classifier: Topic :: Internet :: WWW/HTTP
